{
  "library_name": "DC-DC_CONVERTER", 
  "layer": "15", 
  "attribute1": "00000000", 
  "art": [
    {
      "line_width": 98.0, 
      "startx": -2362.0, 
      "starty": 2362.0, 
      "endy": 2362.0, 
      "endx": 2362.0, 
      "layer": "25", 
      "shape": "segment"
    }, 
    {
      "line_width": 98.0, 
      "startx": 2362.0, 
      "starty": 2362.0, 
      "endy": -2362.0, 
      "endx": 2362.0, 
      "layer": "25", 
      "shape": "segment"
    }, 
    {
      "line_width": 98.0, 
      "startx": 2362.0, 
      "starty": -2362.0, 
      "endy": -2362.0, 
      "endx": -2362.0, 
      "layer": "25", 
      "shape": "segment"
    }, 
    {
      "line_width": 98.0, 
      "startx": -2362.0, 
      "starty": -2362.0, 
      "endy": 2362.0, 
      "endx": -2362.0, 
      "layer": "25", 
      "shape": "segment"
    }, 
    {
      "line_width": 70.0, 
      "startx": -2351.0, 
      "starty": 2351.0, 
      "endy": 2351.0, 
      "endx": 2351.0, 
      "layer": "21", 
      "shape": "segment"
    }, 
    {
      "line_width": 70.0, 
      "startx": 2351.0, 
      "starty": 2351.0, 
      "endy": -2351.0, 
      "endx": 2351.0, 
      "layer": "21", 
      "shape": "segment"
    }, 
    {
      "line_width": 70.0, 
      "startx": 2351.0, 
      "starty": -2351.0, 
      "endy": -2351.0, 
      "endx": -2351.0, 
      "layer": "21", 
      "shape": "segment"
    }, 
    {
      "line_width": 70.0, 
      "startx": -2351.0, 
      "starty": -2351.0, 
      "endy": 2351.0, 
      "endx": -2351.0, 
      "layer": "21", 
      "shape": "segment"
    }, 
    {
      "line_width": 100.0, 
      "startx": -2330.0, 
      "starty": -2240.0, 
      "endy": -2330.0, 
      "endx": -2240.0, 
      "layer": "21", 
      "shape": "segment"
    }, 
    {
      "line_width": 70.0, 
      "startx": -2330.0, 
      "starty": -2140.0, 
      "endy": -2340.0, 
      "endx": -2130.0, 
      "layer": "21", 
      "shape": "segment"
    }
  ], 
  "name": "DC-DC_CONVERTER", 
  "text": [
    {
      "layer": "26", 
      "angle": 0.0, 
      "misc": " \">NAME\"", 
      "sizex": 160.0, 
      "number": "0", 
      "sizey": 160.0, 
      "visible": true, 
      "flag": "N", 
      "text": ">NAME", 
      "y": -2439.0, 
      "x": -2042.0, 
      "rotation": "0", 
      "penwidth": 12.0
    }, 
    {
      "layer": "26", 
      "angle": 0.0, 
      "misc": " \">VALUE\"", 
      "sizex": 160.0, 
      "number": "1", 
      "sizey": 160.0, 
      "visible": true, 
      "flag": "N", 
      "text": ">VALUE", 
      "y": 2822.0, 
      "x": -1882.0, 
      "rotation": "0", 
      "penwidth": 12.0
    }
  ], 
  "timestamp_op": "00000000", 
  "rotation_cost_180": "0", 
  "attribute2": "~~", 
  "y": 0.0, 
  "rotation_cost_misc": "0", 
  "pad": [
    {
      "angle": 0.0, 
      "name": "10", 
      "drill_diam": 0.0, 
      "deltax": 0.0, 
      "deltay": 0.0, 
      "sizex": 397.0, 
      "sizey": 397.0, 
      "drill_x": 0.0, 
      "layer_mask": "00888000", 
      "shape": "rectangle", 
      "drill_y": 0.0, 
      "posy": 862.0, 
      "posx": -1763.0, 
      "shape_code": "R", 
      "type": "SMD", 
      "drill_shape": "circle", 
      "orientation": 0
    }, 
    {
      "angle": 0.0, 
      "name": "7", 
      "drill_diam": 0.0, 
      "deltax": 0.0, 
      "deltay": 0.0, 
      "sizex": 397.0, 
      "sizey": 397.0, 
      "drill_x": 0.0, 
      "layer_mask": "00888000", 
      "shape": "rectangle", 
      "drill_y": 0.0, 
      "posy": 1763.0, 
      "posx": 39.0, 
      "shape_code": "R", 
      "type": "SMD", 
      "drill_shape": "circle", 
      "orientation": 0
    }, 
    {
      "angle": 0.0, 
      "name": "5", 
      "drill_diam": 0.0, 
      "deltax": 0.0, 
      "deltay": 0.0, 
      "sizex": 397.0, 
      "sizey": 397.0, 
      "drill_x": 0.0, 
      "layer_mask": "00888000", 
      "shape": "rectangle", 
      "drill_y": 0.0, 
      "posy": -39.0, 
      "posx": 1814.0, 
      "shape_code": "R", 
      "type": "SMD", 
      "drill_shape": "circle", 
      "orientation": 0
    }, 
    {
      "angle": 0.0, 
      "name": "8", 
      "drill_diam": 0.0, 
      "deltax": 0.0, 
      "deltay": 0.0, 
      "sizex": 397.0, 
      "sizey": 397.0, 
      "drill_x": 0.0, 
      "layer_mask": "00888000", 
      "shape": "rectangle", 
      "drill_y": 0.0, 
      "posy": 1763.0, 
      "posx": -862.0, 
      "shape_code": "R", 
      "type": "SMD", 
      "drill_shape": "circle", 
      "orientation": 0
    }, 
    {
      "angle": 0.0, 
      "name": "6", 
      "drill_diam": 0.0, 
      "deltax": 0.0, 
      "deltay": 0.0, 
      "sizex": 397.0, 
      "sizey": 397.0, 
      "drill_x": 0.0, 
      "layer_mask": "00888000", 
      "shape": "rectangle", 
      "drill_y": 0.0, 
      "posy": 1763.0, 
      "posx": 1814.0, 
      "shape_code": "R", 
      "type": "SMD", 
      "drill_shape": "circle", 
      "orientation": 0
    }, 
    {
      "angle": 0.0, 
      "name": "1", 
      "drill_diam": 0.0, 
      "deltax": 0.0, 
      "deltay": 0.0, 
      "sizex": 397.0, 
      "sizey": 397.0, 
      "drill_x": 0.0, 
      "layer_mask": "00888000", 
      "shape": "rectangle", 
      "drill_y": 0.0, 
      "posy": -39.0, 
      "posx": -1763.0, 
      "shape_code": "R", 
      "type": "SMD", 
      "drill_shape": "circle", 
      "orientation": 0
    }, 
    {
      "angle": 0.0, 
      "name": "9", 
      "drill_diam": 0.0, 
      "deltax": 0.0, 
      "deltay": 0.0, 
      "sizex": 397.0, 
      "sizey": 397.0, 
      "drill_x": 0.0, 
      "layer_mask": "00888000", 
      "shape": "rectangle", 
      "drill_y": 0.0, 
      "posy": 1763.0, 
      "posx": -1763.0, 
      "shape_code": "R", 
      "type": "SMD", 
      "drill_shape": "circle", 
      "orientation": 0
    }, 
    {
      "angle": 1.5707963267948966, 
      "name": "3", 
      "drill_diam": 0.0, 
      "deltax": 0.0, 
      "deltay": 0.0, 
      "sizex": 696.0, 
      "sizey": 1602.0, 
      "drill_x": 0.0, 
      "layer_mask": "00888000", 
      "shape": "rectangle", 
      "drill_y": 0.0, 
      "posy": -1838.0, 
      "posx": 488.0, 
      "shape_code": "R", 
      "type": "SMD", 
      "drill_shape": "circle", 
      "orientation": 900
    }, 
    {
      "angle": 0.0, 
      "name": "4", 
      "drill_diam": 0.0, 
      "deltax": 0.0, 
      "deltay": 0.0, 
      "sizex": 696.0, 
      "sizey": 1602.0, 
      "drill_x": 0.0, 
      "layer_mask": "00888000", 
      "shape": "rectangle", 
      "drill_y": 0.0, 
      "posy": -1389.0, 
      "posx": 1838.0, 
      "shape_code": "R", 
      "type": "SMD", 
      "drill_shape": "circle", 
      "orientation": 0
    }, 
    {
      "angle": 1.5707963267948966, 
      "name": "2", 
      "drill_diam": 0.0, 
      "deltax": 0.0, 
      "deltay": 0.0, 
      "sizex": 696.0, 
      "sizey": 1602.0, 
      "drill_x": 0.0, 
      "layer_mask": "00888000", 
      "shape": "rectangle", 
      "drill_y": 0.0, 
      "posy": -1838.0, 
      "posx": -1311.0, 
      "shape_code": "R", 
      "type": "SMD", 
      "drill_shape": "circle", 
      "orientation": 900
    }
  ], 
  "timestamp": "00000000", 
  "units": "deci-mils", 
  "x": 0.0, 
  "rotation_cost_90": "0", 
  "angle": 0.0, 
  "orientation": "0"
}