{
  "library_name": "LGA8", 
  "layer": "15", 
  "attribute1": "00000000", 
  "art": [
    {
      "line_width": 80.0, 
      "startx": -590.0, 
      "starty": -984.0, 
      "endy": -984.0, 
      "endx": 590.0, 
      "layer": "25", 
      "shape": "segment"
    }, 
    {
      "line_width": 80.0, 
      "startx": 590.0, 
      "starty": -984.0, 
      "endy": 984.0, 
      "endx": 590.0, 
      "layer": "25", 
      "shape": "segment"
    }, 
    {
      "line_width": 80.0, 
      "startx": 590.0, 
      "starty": 984.0, 
      "endy": 984.0, 
      "endx": -590.0, 
      "layer": "25", 
      "shape": "segment"
    }, 
    {
      "line_width": 80.0, 
      "startx": -590.0, 
      "starty": 984.0, 
      "endy": -984.0, 
      "endx": -590.0, 
      "layer": "25", 
      "shape": "segment"
    }, 
    {
      "line_width": 80.0, 
      "startx": -629.0, 
      "starty": 1023.0, 
      "endy": -1023.0, 
      "endx": -629.0, 
      "layer": "21", 
      "shape": "segment"
    }, 
    {
      "line_width": 80.0, 
      "startx": -629.0, 
      "starty": -1023.0, 
      "endy": -1023.0, 
      "endx": 629.0, 
      "layer": "21", 
      "shape": "segment"
    }, 
    {
      "line_width": 80.0, 
      "startx": 629.0, 
      "starty": -1023.0, 
      "endy": 1023.0, 
      "endx": 629.0, 
      "layer": "21", 
      "shape": "segment"
    }, 
    {
      "line_width": 80.0, 
      "startx": 629.0, 
      "starty": 1023.0, 
      "endy": 1023.0, 
      "endx": -629.0, 
      "layer": "21", 
      "shape": "segment"
    }, 
    {
      "line_width": 80.0, 
      "startx": -442.0, 
      "starty": -915.0, 
      "endy": -915.0, 
      "endx": 442.0, 
      "layer": "25", 
      "shape": "segment"
    }, 
    {
      "line_width": 80.0, 
      "startx": -521.0, 
      "starty": 836.0, 
      "endy": -836.0, 
      "endx": -521.0, 
      "layer": "25", 
      "shape": "segment"
    }, 
    {
      "line_width": 80.0, 
      "startx": 521.0, 
      "starty": -836.0, 
      "endy": 836.0, 
      "endx": 521.0, 
      "layer": "25", 
      "shape": "segment"
    }, 
    {
      "line_width": 80.0, 
      "startx": 442.0, 
      "starty": 915.0, 
      "endy": 915.0, 
      "endx": -442.0, 
      "layer": "25", 
      "shape": "segment"
    }, 
    {
      "line_width": 80.0, 
      "layer": "25", 
      "angle": 1.5707963267948966, 
      "start_angle": 1.5707963267948966, 
      "shape": "arc", 
      "r": 79.0, 
      "start_x": "-442", 
      "start_y": "915", 
      "y": "836", 
      "x": "-442"
    }, 
    {
      "line_width": 80.0, 
      "layer": "25", 
      "angle": -1.5707963267948966, 
      "start_angle": 1.5707963267948966, 
      "shape": "arc", 
      "r": 79.0, 
      "start_x": "442", 
      "start_y": "915", 
      "y": "836", 
      "x": "442"
    }, 
    {
      "line_width": 80.0, 
      "layer": "25", 
      "angle": -1.5707963267948966, 
      "start_angle": -1.5707963267948966, 
      "shape": "arc", 
      "r": 79.0, 
      "start_x": "-442", 
      "start_y": "-915", 
      "y": "-836", 
      "x": "-442"
    }, 
    {
      "line_width": 80.0, 
      "layer": "25", 
      "angle": 1.5707963267948966, 
      "start_angle": -1.5707963267948966, 
      "shape": "arc", 
      "r": 79.0, 
      "start_x": "442", 
      "start_y": "-915", 
      "y": "-836", 
      "x": "442"
    }, 
    {
      "line_width": 80.0, 
      "layer": "25", 
      "shape": "circle", 
      "r": 196.0, 
      "y": 472.0, 
      "x": 0.0
    }, 
    {
      "line_width": 160.0, 
      "layer": "21", 
      "shape": "circle", 
      "r": 55.0, 
      "y": -1141.0, 
      "x": -866.0
    }
  ], 
  "name": "LGA8", 
  "keyword": [
    " <b>LGA8 3x5mm 1.25mm Pitch</b>"
  ], 
  "text": [
    {
      "layer": "26", 
      "angle": 0.0, 
      "misc": " \">NAME\"", 
      "sizex": 320.0, 
      "number": "0", 
      "sizey": 320.0, 
      "visible": true, 
      "flag": "N", 
      "text": ">NAME", 
      "y": -940.0, 
      "x": 40.0, 
      "rotation": "0", 
      "penwidth": 57.0
    }, 
    {
      "layer": "26", 
      "angle": 0.0, 
      "misc": " \">VALUE\"", 
      "sizex": 160.0, 
      "number": "1", 
      "sizey": 160.0, 
      "visible": true, 
      "flag": "N", 
      "text": ">VALUE", 
      "y": 1380.0, 
      "x": -120.0, 
      "rotation": "0", 
      "penwidth": 16.0
    }
  ], 
  "timestamp_op": "00000000", 
  "rotation_cost_180": "0", 
  "attribute2": "~~", 
  "y": 0.0, 
  "rotation_cost_misc": "0", 
  "pad": [
    {
      "angle": 0.0, 
      "name": "P$1", 
      "drill_diam": 0.0, 
      "deltax": 0.0, 
      "deltay": 0.0, 
      "sizex": 748.0, 
      "sizey": 236.0, 
      "drill_x": 0.0, 
      "layer_mask": "00888000", 
      "shape": "rectangle", 
      "drill_y": 0.0, 
      "posy": -738.0, 
      "posx": -590.0, 
      "shape_code": "R", 
      "type": "SMD", 
      "drill_shape": "circle", 
      "orientation": 0
    }, 
    {
      "angle": 0.0, 
      "name": "P$2", 
      "drill_diam": 0.0, 
      "deltax": 0.0, 
      "deltay": 0.0, 
      "sizex": 748.0, 
      "sizey": 236.0, 
      "drill_x": 0.0, 
      "layer_mask": "00888000", 
      "shape": "rectangle", 
      "drill_y": 0.0, 
      "posy": -246.0, 
      "posx": -590.0, 
      "shape_code": "R", 
      "type": "SMD", 
      "drill_shape": "circle", 
      "orientation": 0
    }, 
    {
      "angle": 0.0, 
      "name": "P$3", 
      "drill_diam": 0.0, 
      "deltax": 0.0, 
      "deltay": 0.0, 
      "sizex": 748.0, 
      "sizey": 236.0, 
      "drill_x": 0.0, 
      "layer_mask": "00888000", 
      "shape": "rectangle", 
      "drill_y": 0.0, 
      "posy": 246.0, 
      "posx": -590.0, 
      "shape_code": "R", 
      "type": "SMD", 
      "drill_shape": "circle", 
      "orientation": 0
    }, 
    {
      "angle": 0.0, 
      "name": "P$4", 
      "drill_diam": 0.0, 
      "deltax": 0.0, 
      "deltay": 0.0, 
      "sizex": 748.0, 
      "sizey": 236.0, 
      "drill_x": 0.0, 
      "layer_mask": "00888000", 
      "shape": "rectangle", 
      "drill_y": 0.0, 
      "posy": 738.0, 
      "posx": -590.0, 
      "shape_code": "R", 
      "type": "SMD", 
      "drill_shape": "circle", 
      "orientation": 0
    }, 
    {
      "angle": 0.0, 
      "name": "P$5", 
      "drill_diam": 0.0, 
      "deltax": 0.0, 
      "deltay": 0.0, 
      "sizex": 748.0, 
      "sizey": 236.0, 
      "drill_x": 0.0, 
      "layer_mask": "00888000", 
      "shape": "rectangle", 
      "drill_y": 0.0, 
      "posy": 738.0, 
      "posx": 590.0, 
      "shape_code": "R", 
      "type": "SMD", 
      "drill_shape": "circle", 
      "orientation": 0
    }, 
    {
      "angle": 0.0, 
      "name": "P$6", 
      "drill_diam": 0.0, 
      "deltax": 0.0, 
      "deltay": 0.0, 
      "sizex": 748.0, 
      "sizey": 236.0, 
      "drill_x": 0.0, 
      "layer_mask": "00888000", 
      "shape": "rectangle", 
      "drill_y": 0.0, 
      "posy": 246.0, 
      "posx": 590.0, 
      "shape_code": "R", 
      "type": "SMD", 
      "drill_shape": "circle", 
      "orientation": 0
    }, 
    {
      "angle": 0.0, 
      "name": "P$7", 
      "drill_diam": 0.0, 
      "deltax": 0.0, 
      "deltay": 0.0, 
      "sizex": 748.0, 
      "sizey": 236.0, 
      "drill_x": 0.0, 
      "layer_mask": "00888000", 
      "shape": "rectangle", 
      "drill_y": 0.0, 
      "posy": -246.0, 
      "posx": 590.0, 
      "shape_code": "R", 
      "type": "SMD", 
      "drill_shape": "circle", 
      "orientation": 0
    }, 
    {
      "angle": 0.0, 
      "name": "P$8", 
      "drill_diam": 0.0, 
      "deltax": 0.0, 
      "deltay": 0.0, 
      "sizex": 748.0, 
      "sizey": 236.0, 
      "drill_x": 0.0, 
      "layer_mask": "00888000", 
      "shape": "rectangle", 
      "drill_y": 0.0, 
      "posy": -738.0, 
      "posx": 590.0, 
      "shape_code": "R", 
      "type": "SMD", 
      "drill_shape": "circle", 
      "orientation": 0
    }
  ], 
  "timestamp": "00000000", 
  "units": "deci-mils", 
  "x": 0.0, 
  "rotation_cost_90": "0", 
  "angle": 0.0, 
  "orientation": "0"
}