{
  "library_name": "2X6_SMD", 
  "layer": "15", 
  "attribute1": "00000000", 
  "art": [
    {
      "line_width": 50.0, 
      "startx": -2500.0, 
      "starty": 984.0, 
      "endy": -984.0, 
      "endx": -2500.0, 
      "layer": "25", 
      "shape": "segment"
    }, 
    {
      "line_width": 50.0, 
      "startx": -2500.0, 
      "starty": -984.0, 
      "endy": -984.0, 
      "endx": 3500.0, 
      "layer": "25", 
      "shape": "segment"
    }, 
    {
      "line_width": 50.0, 
      "startx": 3500.0, 
      "starty": -984.0, 
      "endy": 984.0, 
      "endx": 3500.0, 
      "layer": "25", 
      "shape": "segment"
    }, 
    {
      "line_width": 50.0, 
      "startx": 3500.0, 
      "starty": 984.0, 
      "endy": 984.0, 
      "endx": -2500.0, 
      "layer": "25", 
      "shape": "segment"
    }, 
    {
      "line_width": 50.0, 
      "layer": "25", 
      "shape": "circle", 
      "r": 275.0, 
      "y": -500.0, 
      "x": -1000.0
    }, 
    {
      "line_width": 50.0, 
      "layer": "25", 
      "shape": "circle", 
      "r": 275.0, 
      "y": -500.0, 
      "x": -2000.0
    }, 
    {
      "line_width": 50.0, 
      "layer": "25", 
      "shape": "circle", 
      "r": 275.0, 
      "y": 500.0, 
      "x": -2000.0
    }, 
    {
      "line_width": 50.0, 
      "layer": "25", 
      "shape": "circle", 
      "r": 275.0, 
      "y": 500.0, 
      "x": -1000.0
    }, 
    {
      "line_width": 50.0, 
      "layer": "25", 
      "shape": "circle", 
      "r": 275.0, 
      "y": 500.0, 
      "x": 0.0
    }, 
    {
      "line_width": 50.0, 
      "layer": "25", 
      "shape": "circle", 
      "r": 275.0, 
      "y": -500.0, 
      "x": 0.0
    }, 
    {
      "line_width": 50.0, 
      "layer": "25", 
      "shape": "circle", 
      "r": 275.0, 
      "y": 500.0, 
      "x": 1000.0
    }, 
    {
      "line_width": 50.0, 
      "layer": "25", 
      "shape": "circle", 
      "r": 275.0, 
      "y": -500.0, 
      "x": 1000.0
    }, 
    {
      "line_width": 50.0, 
      "layer": "25", 
      "shape": "circle", 
      "r": 275.0, 
      "y": 500.0, 
      "x": 2000.0
    }, 
    {
      "line_width": 50.0, 
      "layer": "25", 
      "shape": "circle", 
      "r": 275.0, 
      "y": -500.0, 
      "x": 2000.0
    }, 
    {
      "line_width": 50.0, 
      "layer": "25", 
      "shape": "circle", 
      "r": 275.0, 
      "y": 500.0, 
      "x": 3000.0
    }, 
    {
      "line_width": 50.0, 
      "layer": "25", 
      "shape": "circle", 
      "r": 275.0, 
      "y": -500.0, 
      "x": 3000.0
    }, 
    {
      "line_width": 50.0, 
      "startx": -1118.0, 
      "starty": -1003.0, 
      "endy": -1003.0, 
      "endx": -881.0, 
      "layer": "25", 
      "shape": "segment"
    }, 
    {
      "line_width": 50.0, 
      "startx": -881.0, 
      "starty": -1003.0, 
      "endy": -1318.0, 
      "endx": -881.0, 
      "layer": "25", 
      "shape": "segment"
    }, 
    {
      "line_width": 50.0, 
      "startx": -881.0, 
      "starty": -1318.0, 
      "endy": -1318.0, 
      "endx": -1118.0, 
      "layer": "25", 
      "shape": "segment"
    }, 
    {
      "line_width": 50.0, 
      "startx": -1118.0, 
      "starty": -1318.0, 
      "endy": -1003.0, 
      "endx": -1118.0, 
      "layer": "25", 
      "shape": "segment"
    }, 
    {
      "line_width": 50.0, 
      "startx": -2118.0, 
      "starty": -1003.0, 
      "endy": -1003.0, 
      "endx": -1881.0, 
      "layer": "25", 
      "shape": "segment"
    }, 
    {
      "line_width": 50.0, 
      "startx": -1881.0, 
      "starty": -1003.0, 
      "endy": -1318.0, 
      "endx": -1881.0, 
      "layer": "25", 
      "shape": "segment"
    }, 
    {
      "line_width": 50.0, 
      "startx": -1881.0, 
      "starty": -1318.0, 
      "endy": -1318.0, 
      "endx": -2118.0, 
      "layer": "25", 
      "shape": "segment"
    }, 
    {
      "line_width": 50.0, 
      "startx": -2118.0, 
      "starty": -1318.0, 
      "endy": -1003.0, 
      "endx": -2118.0, 
      "layer": "25", 
      "shape": "segment"
    }, 
    {
      "line_width": 50.0, 
      "startx": -118.0, 
      "starty": -1003.0, 
      "endy": -1003.0, 
      "endx": 118.0, 
      "layer": "25", 
      "shape": "segment"
    }, 
    {
      "line_width": 50.0, 
      "startx": 118.0, 
      "starty": -1003.0, 
      "endy": -1318.0, 
      "endx": 118.0, 
      "layer": "25", 
      "shape": "segment"
    }, 
    {
      "line_width": 50.0, 
      "startx": 118.0, 
      "starty": -1318.0, 
      "endy": -1318.0, 
      "endx": -118.0, 
      "layer": "25", 
      "shape": "segment"
    }, 
    {
      "line_width": 50.0, 
      "startx": -118.0, 
      "starty": -1318.0, 
      "endy": -1003.0, 
      "endx": -118.0, 
      "layer": "25", 
      "shape": "segment"
    }, 
    {
      "line_width": 50.0, 
      "startx": -2118.0, 
      "starty": 1318.0, 
      "endy": 1318.0, 
      "endx": -1881.0, 
      "layer": "25", 
      "shape": "segment"
    }, 
    {
      "line_width": 50.0, 
      "startx": -1881.0, 
      "starty": 1318.0, 
      "endy": 1003.0, 
      "endx": -1881.0, 
      "layer": "25", 
      "shape": "segment"
    }, 
    {
      "line_width": 50.0, 
      "startx": -1881.0, 
      "starty": 1003.0, 
      "endy": 1003.0, 
      "endx": -2118.0, 
      "layer": "25", 
      "shape": "segment"
    }, 
    {
      "line_width": 50.0, 
      "startx": -2118.0, 
      "starty": 1003.0, 
      "endy": 1318.0, 
      "endx": -2118.0, 
      "layer": "25", 
      "shape": "segment"
    }, 
    {
      "line_width": 50.0, 
      "startx": -1118.0, 
      "starty": 1318.0, 
      "endy": 1318.0, 
      "endx": -881.0, 
      "layer": "25", 
      "shape": "segment"
    }, 
    {
      "line_width": 50.0, 
      "startx": -881.0, 
      "starty": 1318.0, 
      "endy": 1003.0, 
      "endx": -881.0, 
      "layer": "25", 
      "shape": "segment"
    }, 
    {
      "line_width": 50.0, 
      "startx": -881.0, 
      "starty": 1003.0, 
      "endy": 1003.0, 
      "endx": -1118.0, 
      "layer": "25", 
      "shape": "segment"
    }, 
    {
      "line_width": 50.0, 
      "startx": -1118.0, 
      "starty": 1003.0, 
      "endy": 1318.0, 
      "endx": -1118.0, 
      "layer": "25", 
      "shape": "segment"
    }, 
    {
      "line_width": 50.0, 
      "startx": -118.0, 
      "starty": 1318.0, 
      "endy": 1318.0, 
      "endx": 118.0, 
      "layer": "25", 
      "shape": "segment"
    }, 
    {
      "line_width": 50.0, 
      "startx": 118.0, 
      "starty": 1318.0, 
      "endy": 1003.0, 
      "endx": 118.0, 
      "layer": "25", 
      "shape": "segment"
    }, 
    {
      "line_width": 50.0, 
      "startx": 118.0, 
      "starty": 1003.0, 
      "endy": 1003.0, 
      "endx": -118.0, 
      "layer": "25", 
      "shape": "segment"
    }, 
    {
      "line_width": 50.0, 
      "startx": -118.0, 
      "starty": 1003.0, 
      "endy": 1318.0, 
      "endx": -118.0, 
      "layer": "25", 
      "shape": "segment"
    }, 
    {
      "line_width": 50.0, 
      "startx": 881.0, 
      "starty": -1003.0, 
      "endy": -1003.0, 
      "endx": 1118.0, 
      "layer": "25", 
      "shape": "segment"
    }, 
    {
      "line_width": 50.0, 
      "startx": 1118.0, 
      "starty": -1003.0, 
      "endy": -1318.0, 
      "endx": 1118.0, 
      "layer": "25", 
      "shape": "segment"
    }, 
    {
      "line_width": 50.0, 
      "startx": 1118.0, 
      "starty": -1318.0, 
      "endy": -1318.0, 
      "endx": 881.0, 
      "layer": "25", 
      "shape": "segment"
    }, 
    {
      "line_width": 50.0, 
      "startx": 881.0, 
      "starty": -1318.0, 
      "endy": -1003.0, 
      "endx": 881.0, 
      "layer": "25", 
      "shape": "segment"
    }, 
    {
      "line_width": 50.0, 
      "startx": 881.0, 
      "starty": 1318.0, 
      "endy": 1318.0, 
      "endx": 1118.0, 
      "layer": "25", 
      "shape": "segment"
    }, 
    {
      "line_width": 50.0, 
      "startx": 1118.0, 
      "starty": 1318.0, 
      "endy": 1003.0, 
      "endx": 1118.0, 
      "layer": "25", 
      "shape": "segment"
    }, 
    {
      "line_width": 50.0, 
      "startx": 1118.0, 
      "starty": 1003.0, 
      "endy": 1003.0, 
      "endx": 881.0, 
      "layer": "25", 
      "shape": "segment"
    }, 
    {
      "line_width": 50.0, 
      "startx": 881.0, 
      "starty": 1003.0, 
      "endy": 1318.0, 
      "endx": 881.0, 
      "layer": "25", 
      "shape": "segment"
    }, 
    {
      "line_width": 50.0, 
      "startx": 1881.0, 
      "starty": -1003.0, 
      "endy": -1003.0, 
      "endx": 2118.0, 
      "layer": "25", 
      "shape": "segment"
    }, 
    {
      "line_width": 50.0, 
      "startx": 2118.0, 
      "starty": -1003.0, 
      "endy": -1318.0, 
      "endx": 2118.0, 
      "layer": "25", 
      "shape": "segment"
    }, 
    {
      "line_width": 50.0, 
      "startx": 2118.0, 
      "starty": -1318.0, 
      "endy": -1318.0, 
      "endx": 1881.0, 
      "layer": "25", 
      "shape": "segment"
    }, 
    {
      "line_width": 50.0, 
      "startx": 1881.0, 
      "starty": -1318.0, 
      "endy": -1003.0, 
      "endx": 1881.0, 
      "layer": "25", 
      "shape": "segment"
    }, 
    {
      "line_width": 50.0, 
      "startx": 1881.0, 
      "starty": 1318.0, 
      "endy": 1318.0, 
      "endx": 2118.0, 
      "layer": "25", 
      "shape": "segment"
    }, 
    {
      "line_width": 50.0, 
      "startx": 2118.0, 
      "starty": 1318.0, 
      "endy": 1003.0, 
      "endx": 2118.0, 
      "layer": "25", 
      "shape": "segment"
    }, 
    {
      "line_width": 50.0, 
      "startx": 2118.0, 
      "starty": 1003.0, 
      "endy": 1003.0, 
      "endx": 1881.0, 
      "layer": "25", 
      "shape": "segment"
    }, 
    {
      "line_width": 50.0, 
      "startx": 1881.0, 
      "starty": 1003.0, 
      "endy": 1318.0, 
      "endx": 1881.0, 
      "layer": "25", 
      "shape": "segment"
    }, 
    {
      "line_width": 50.0, 
      "startx": 2881.0, 
      "starty": -1003.0, 
      "endy": -1003.0, 
      "endx": 3118.0, 
      "layer": "25", 
      "shape": "segment"
    }, 
    {
      "line_width": 50.0, 
      "startx": 3118.0, 
      "starty": -1003.0, 
      "endy": -1318.0, 
      "endx": 3118.0, 
      "layer": "25", 
      "shape": "segment"
    }, 
    {
      "line_width": 50.0, 
      "startx": 3118.0, 
      "starty": -1318.0, 
      "endy": -1318.0, 
      "endx": 2881.0, 
      "layer": "25", 
      "shape": "segment"
    }, 
    {
      "line_width": 50.0, 
      "startx": 2881.0, 
      "starty": -1318.0, 
      "endy": -1003.0, 
      "endx": 2881.0, 
      "layer": "25", 
      "shape": "segment"
    }, 
    {
      "line_width": 50.0, 
      "startx": 2881.0, 
      "starty": 1318.0, 
      "endy": 1318.0, 
      "endx": 3118.0, 
      "layer": "25", 
      "shape": "segment"
    }, 
    {
      "line_width": 50.0, 
      "startx": 3118.0, 
      "starty": 1318.0, 
      "endy": 1003.0, 
      "endx": 3118.0, 
      "layer": "25", 
      "shape": "segment"
    }, 
    {
      "line_width": 50.0, 
      "startx": 3118.0, 
      "starty": 1003.0, 
      "endy": 1003.0, 
      "endx": 2881.0, 
      "layer": "25", 
      "shape": "segment"
    }, 
    {
      "line_width": 50.0, 
      "startx": 2881.0, 
      "starty": 1003.0, 
      "endy": 1318.0, 
      "endx": 2881.0, 
      "layer": "25", 
      "shape": "segment"
    }
  ], 
  "name": "2X6_SMD", 
  "text": [
    {
      "layer": "25", 
      "angle": 0.0, 
      "misc": " \"ref**\"", 
      "sizex": 0.0, 
      "number": "0", 
      "sizey": 0.0, 
      "visible": false, 
      "flag": "N", 
      "text": "ref**", 
      "y": 0.0, 
      "x": 0.0, 
      "rotation": "0", 
      "penwidth": 0.0
    }, 
    {
      "layer": "26", 
      "angle": 0.0, 
      "misc": " \"val**\"", 
      "sizex": 0.0, 
      "number": "1", 
      "sizey": 0.0, 
      "visible": false, 
      "flag": "N", 
      "text": "val**", 
      "y": 0.0, 
      "x": 0.0, 
      "rotation": "0", 
      "penwidth": 0.0
    }, 
    {
      "layer": "26", 
      "angle": 0.0, 
      "misc": " \">Name\"", 
      "sizex": 160.0, 
      "number": "2", 
      "sizey": 160.0, 
      "visible": true, 
      "flag": "N", 
      "text": ">Name", 
      "y": 41.0, 
      "x": -2058.0, 
      "rotation": "0", 
      "penwidth": 12.0
    }, 
    {
      "layer": "26", 
      "angle": 0.0, 
      "misc": " \">Value\"", 
      "sizex": 160.0, 
      "number": "3", 
      "sizey": 160.0, 
      "visible": true, 
      "flag": "N", 
      "text": ">Value", 
      "y": 240.0, 
      "x": -1898.0, 
      "rotation": "0", 
      "penwidth": 12.0
    }
  ], 
  "timestamp_op": "00000000", 
  "rotation_cost_180": "0", 
  "attribute2": "~~", 
  "y": 0.0, 
  "rotation_cost_misc": "0", 
  "pad": [
    {
      "angle": 0.0, 
      "name": "1", 
      "drill_diam": 0.0, 
      "deltax": 0.0, 
      "deltay": 0.0, 
      "sizex": 401.0, 
      "sizey": 748.0, 
      "drill_x": 0.0, 
      "layer_mask": "00888000", 
      "shape": "rectangle", 
      "drill_y": 0.0, 
      "posy": 1122.0, 
      "posx": -2000.0, 
      "shape_code": "R", 
      "type": "SMD", 
      "drill_shape": "circle", 
      "orientation": 0
    }, 
    {
      "angle": 0.0, 
      "name": "2", 
      "drill_diam": 0.0, 
      "deltax": 0.0, 
      "deltay": 0.0, 
      "sizex": 401.0, 
      "sizey": 748.0, 
      "drill_x": 0.0, 
      "layer_mask": "00888000", 
      "shape": "rectangle", 
      "drill_y": 0.0, 
      "posy": -1122.0, 
      "posx": -2000.0, 
      "shape_code": "R", 
      "type": "SMD", 
      "drill_shape": "circle", 
      "orientation": 0
    }, 
    {
      "angle": 0.0, 
      "name": "3", 
      "drill_diam": 0.0, 
      "deltax": 0.0, 
      "deltay": 0.0, 
      "sizex": 401.0, 
      "sizey": 748.0, 
      "drill_x": 0.0, 
      "layer_mask": "00888000", 
      "shape": "rectangle", 
      "drill_y": 0.0, 
      "posy": 1122.0, 
      "posx": -1000.0, 
      "shape_code": "R", 
      "type": "SMD", 
      "drill_shape": "circle", 
      "orientation": 0
    }, 
    {
      "angle": 0.0, 
      "name": "4", 
      "drill_diam": 0.0, 
      "deltax": 0.0, 
      "deltay": 0.0, 
      "sizex": 401.0, 
      "sizey": 748.0, 
      "drill_x": 0.0, 
      "layer_mask": "00888000", 
      "shape": "rectangle", 
      "drill_y": 0.0, 
      "posy": -1122.0, 
      "posx": -1000.0, 
      "shape_code": "R", 
      "type": "SMD", 
      "drill_shape": "circle", 
      "orientation": 0
    }, 
    {
      "angle": 0.0, 
      "name": "5", 
      "drill_diam": 0.0, 
      "deltax": 0.0, 
      "deltay": 0.0, 
      "sizex": 401.0, 
      "sizey": 748.0, 
      "drill_x": 0.0, 
      "layer_mask": "00888000", 
      "shape": "rectangle", 
      "drill_y": 0.0, 
      "posy": 1122.0, 
      "posx": 0.0, 
      "shape_code": "R", 
      "type": "SMD", 
      "drill_shape": "circle", 
      "orientation": 0
    }, 
    {
      "angle": 0.0, 
      "name": "6", 
      "drill_diam": 0.0, 
      "deltax": 0.0, 
      "deltay": 0.0, 
      "sizex": 401.0, 
      "sizey": 748.0, 
      "drill_x": 0.0, 
      "layer_mask": "00888000", 
      "shape": "rectangle", 
      "drill_y": 0.0, 
      "posy": -1122.0, 
      "posx": 0.0, 
      "shape_code": "R", 
      "type": "SMD", 
      "drill_shape": "circle", 
      "orientation": 0
    }, 
    {
      "angle": 0.0, 
      "name": "7", 
      "drill_diam": 0.0, 
      "deltax": 0.0, 
      "deltay": 0.0, 
      "sizex": 401.0, 
      "sizey": 748.0, 
      "drill_x": 0.0, 
      "layer_mask": "00888000", 
      "shape": "rectangle", 
      "drill_y": 0.0, 
      "posy": 1122.0, 
      "posx": 1000.0, 
      "shape_code": "R", 
      "type": "SMD", 
      "drill_shape": "circle", 
      "orientation": 0
    }, 
    {
      "angle": 0.0, 
      "name": "8", 
      "drill_diam": 0.0, 
      "deltax": 0.0, 
      "deltay": 0.0, 
      "sizex": 401.0, 
      "sizey": 748.0, 
      "drill_x": 0.0, 
      "layer_mask": "00888000", 
      "shape": "rectangle", 
      "drill_y": 0.0, 
      "posy": -1122.0, 
      "posx": 1000.0, 
      "shape_code": "R", 
      "type": "SMD", 
      "drill_shape": "circle", 
      "orientation": 0
    }, 
    {
      "angle": 0.0, 
      "name": "9", 
      "drill_diam": 0.0, 
      "deltax": 0.0, 
      "deltay": 0.0, 
      "sizex": 401.0, 
      "sizey": 748.0, 
      "drill_x": 0.0, 
      "layer_mask": "00888000", 
      "shape": "rectangle", 
      "drill_y": 0.0, 
      "posy": 1122.0, 
      "posx": 2000.0, 
      "shape_code": "R", 
      "type": "SMD", 
      "drill_shape": "circle", 
      "orientation": 0
    }, 
    {
      "angle": 0.0, 
      "name": "10", 
      "drill_diam": 0.0, 
      "deltax": 0.0, 
      "deltay": 0.0, 
      "sizex": 401.0, 
      "sizey": 748.0, 
      "drill_x": 0.0, 
      "layer_mask": "00888000", 
      "shape": "rectangle", 
      "drill_y": 0.0, 
      "posy": -1122.0, 
      "posx": 2000.0, 
      "shape_code": "R", 
      "type": "SMD", 
      "drill_shape": "circle", 
      "orientation": 0
    }, 
    {
      "angle": 0.0, 
      "name": "11", 
      "drill_diam": 0.0, 
      "deltax": 0.0, 
      "deltay": 0.0, 
      "sizex": 401.0, 
      "sizey": 748.0, 
      "drill_x": 0.0, 
      "layer_mask": "00888000", 
      "shape": "rectangle", 
      "drill_y": 0.0, 
      "posy": 1122.0, 
      "posx": 3000.0, 
      "shape_code": "R", 
      "type": "SMD", 
      "drill_shape": "circle", 
      "orientation": 0
    }, 
    {
      "angle": 0.0, 
      "name": "12", 
      "drill_diam": 0.0, 
      "deltax": 0.0, 
      "deltay": 0.0, 
      "sizex": 401.0, 
      "sizey": 748.0, 
      "drill_x": 0.0, 
      "layer_mask": "00888000", 
      "shape": "rectangle", 
      "drill_y": 0.0, 
      "posy": -1122.0, 
      "posx": 3000.0, 
      "shape_code": "R", 
      "type": "SMD", 
      "drill_shape": "circle", 
      "orientation": 0
    }
  ], 
  "timestamp": "00000000", 
  "units": "deci-mils", 
  "x": 0.0, 
  "rotation_cost_90": "0", 
  "angle": 0.0, 
  "orientation": "0"
}