{
  "library_name": "M25H", 
  "layer": "15", 
  "attribute1": "00000000", 
  "art": [
    {
      "line_width": 60.0, 
      "startx": 7600.0, 
      "starty": 6900.0, 
      "endy": 6900.0, 
      "endx": 7500.0, 
      "layer": "21", 
      "shape": "segment"
    }, 
    {
      "line_width": 60.0, 
      "layer": "21", 
      "angle": -1.5707963267948966, 
      "start_angle": 1.5707963267948966, 
      "shape": "arc", 
      "r": 201.0, 
      "start_x": "7600", 
      "start_y": "6900", 
      "y": "6699", 
      "x": "7600"
    }, 
    {
      "line_width": 60.0, 
      "layer": "21", 
      "angle": -1.5707963267948966, 
      "start_angle": 3.136592695255835, 
      "shape": "arc", 
      "r": 200.0024999843752, 
      "start_x": "-7800", 
      "start_y": "6700", 
      "y": "6699", 
      "x": "-7600"
    }, 
    {
      "line_width": 60.0, 
      "startx": 7650.0, 
      "starty": 4600.0, 
      "endy": 4600.0, 
      "endx": -7650.0, 
      "layer": "21", 
      "shape": "segment"
    }, 
    {
      "line_width": 60.0, 
      "startx": 10450.0, 
      "starty": 3000.0, 
      "endy": 3000.0, 
      "endx": 8450.0, 
      "layer": "21", 
      "shape": "segment"
    }, 
    {
      "line_width": 60.0, 
      "startx": 10450.0, 
      "starty": 3000.0, 
      "endy": 4200.0, 
      "endx": 10450.0, 
      "layer": "21", 
      "shape": "segment"
    }, 
    {
      "line_width": 60.0, 
      "startx": 10450.0, 
      "starty": 3000.0, 
      "endy": 2950.0, 
      "endx": 10450.0, 
      "layer": "21", 
      "shape": "segment"
    }, 
    {
      "line_width": 60.0, 
      "startx": 10450.0, 
      "starty": 4200.0, 
      "endy": 4400.0, 
      "endx": 10450.0, 
      "layer": "21", 
      "shape": "segment"
    }, 
    {
      "line_width": 60.0, 
      "startx": 10450.0, 
      "starty": 4400.0, 
      "endy": 4600.0, 
      "endx": 10450.0, 
      "layer": "21", 
      "shape": "segment"
    }, 
    {
      "line_width": 60.0, 
      "startx": -10450.0, 
      "starty": 4600.0, 
      "endy": 4400.0, 
      "endx": -10450.0, 
      "layer": "21", 
      "shape": "segment"
    }, 
    {
      "line_width": 60.0, 
      "startx": -10450.0, 
      "starty": 4400.0, 
      "endy": 4200.0, 
      "endx": -10450.0, 
      "layer": "21", 
      "shape": "segment"
    }, 
    {
      "line_width": 60.0, 
      "startx": -10450.0, 
      "starty": 4200.0, 
      "endy": 3000.0, 
      "endx": -10450.0, 
      "layer": "21", 
      "shape": "segment"
    }, 
    {
      "line_width": 60.0, 
      "startx": -10450.0, 
      "starty": 3000.0, 
      "endy": 2950.0, 
      "endx": -10450.0, 
      "layer": "21", 
      "shape": "segment"
    }, 
    {
      "line_width": 60.0, 
      "startx": 8450.0, 
      "starty": 4200.0, 
      "endy": 4400.0, 
      "endx": 8450.0, 
      "layer": "21", 
      "shape": "segment"
    }, 
    {
      "line_width": 60.0, 
      "startx": 8450.0, 
      "starty": 4200.0, 
      "endy": 4200.0, 
      "endx": 8400.0, 
      "layer": "21", 
      "shape": "segment"
    }, 
    {
      "line_width": 60.0, 
      "layer": "21", 
      "angle": 1.5707963267948966, 
      "start_angle": -1.5707963267948966, 
      "shape": "arc", 
      "r": 249.0, 
      "start_x": "8150", 
      "start_y": "3000", 
      "y": "3249", 
      "x": "8150"
    }, 
    {
      "line_width": 60.0, 
      "startx": 8450.0, 
      "starty": 3000.0, 
      "endy": 3000.0, 
      "endx": 8100.0, 
      "layer": "21", 
      "shape": "segment"
    }, 
    {
      "line_width": 60.0, 
      "startx": 8100.0, 
      "starty": 3000.0, 
      "endy": 3000.0, 
      "endx": 8000.0, 
      "layer": "21", 
      "shape": "segment"
    }, 
    {
      "line_width": 60.0, 
      "startx": 8400.0, 
      "starty": 3250.0, 
      "endy": 4200.0, 
      "endx": 8400.0, 
      "layer": "21", 
      "shape": "segment"
    }, 
    {
      "line_width": 60.0, 
      "startx": 8000.0, 
      "starty": 3000.0, 
      "endy": 2700.0, 
      "endx": 8000.0, 
      "layer": "21", 
      "shape": "segment"
    }, 
    {
      "line_width": 60.0, 
      "startx": 8000.0, 
      "starty": 3000.0, 
      "endy": 3000.0, 
      "endx": -8000.0, 
      "layer": "21", 
      "shape": "segment"
    }, 
    {
      "line_width": 60.0, 
      "startx": 8000.0, 
      "starty": 2700.0, 
      "endy": 2700.0, 
      "endx": -8000.0, 
      "layer": "21", 
      "shape": "segment"
    }, 
    {
      "line_width": 60.0, 
      "startx": -8000.0, 
      "starty": 3000.0, 
      "endy": 2700.0, 
      "endx": -8000.0, 
      "layer": "21", 
      "shape": "segment"
    }, 
    {
      "line_width": 60.0, 
      "startx": -8000.0, 
      "starty": 3000.0, 
      "endy": 3000.0, 
      "endx": -8100.0, 
      "layer": "21", 
      "shape": "segment"
    }, 
    {
      "line_width": 60.0, 
      "startx": -8100.0, 
      "starty": 3000.0, 
      "endy": 3000.0, 
      "endx": -8450.0, 
      "layer": "21", 
      "shape": "segment"
    }, 
    {
      "line_width": 60.0, 
      "startx": -8450.0, 
      "starty": 4200.0, 
      "endy": 4400.0, 
      "endx": -8450.0, 
      "layer": "21", 
      "shape": "segment"
    }, 
    {
      "line_width": 60.0, 
      "startx": -8400.0, 
      "starty": 3250.0, 
      "endy": 4200.0, 
      "endx": -8400.0, 
      "layer": "21", 
      "shape": "segment"
    }, 
    {
      "line_width": 60.0, 
      "startx": -8400.0, 
      "starty": 4200.0, 
      "endy": 4200.0, 
      "endx": -8450.0, 
      "layer": "21", 
      "shape": "segment"
    }, 
    {
      "line_width": 60.0, 
      "layer": "21", 
      "angle": 1.5707963267948966, 
      "start_angle": 3.1375926749229217, 
      "shape": "arc", 
      "r": 250.00199999200007, 
      "start_x": "-8400", 
      "start_y": "3250", 
      "y": "3249", 
      "x": "-8150"
    }, 
    {
      "line_width": 60.0, 
      "startx": 10200.0, 
      "starty": -1250.0, 
      "endy": -1000.0, 
      "endx": 10450.0, 
      "layer": "21", 
      "shape": "segment"
    }, 
    {
      "line_width": 60.0, 
      "startx": 10450.0, 
      "starty": -1000.0, 
      "endy": 2950.0, 
      "endx": 10450.0, 
      "layer": "21", 
      "shape": "segment"
    }, 
    {
      "line_width": 60.0, 
      "startx": 8300.0, 
      "starty": -1250.0, 
      "endy": -1250.0, 
      "endx": 10200.0, 
      "layer": "21", 
      "shape": "segment"
    }, 
    {
      "line_width": 60.0, 
      "startx": 8300.0, 
      "starty": -1250.0, 
      "endy": -1050.0, 
      "endx": 8100.0, 
      "layer": "21", 
      "shape": "segment"
    }, 
    {
      "line_width": 60.0, 
      "startx": 8100.0, 
      "starty": -1050.0, 
      "endy": 3000.0, 
      "endx": 8100.0, 
      "layer": "21", 
      "shape": "segment"
    }, 
    {
      "line_width": 60.0, 
      "startx": -8100.0, 
      "starty": -1050.0, 
      "endy": 3000.0, 
      "endx": -8100.0, 
      "layer": "21", 
      "shape": "segment"
    }, 
    {
      "line_width": 60.0, 
      "startx": -8100.0, 
      "starty": -1050.0, 
      "endy": -1250.0, 
      "endx": -8300.0, 
      "layer": "21", 
      "shape": "segment"
    }, 
    {
      "line_width": 60.0, 
      "startx": -8300.0, 
      "starty": -1250.0, 
      "endy": -1250.0, 
      "endx": -10250.0, 
      "layer": "21", 
      "shape": "segment"
    }, 
    {
      "line_width": 60.0, 
      "startx": -10250.0, 
      "starty": -1250.0, 
      "endy": -1050.0, 
      "endx": -10450.0, 
      "layer": "21", 
      "shape": "segment"
    }, 
    {
      "line_width": 60.0, 
      "startx": -10450.0, 
      "starty": -1050.0, 
      "endy": 2950.0, 
      "endx": -10450.0, 
      "layer": "21", 
      "shape": "segment"
    }, 
    {
      "line_width": 320.0, 
      "startx": -1090.0, 
      "starty": -450.0, 
      "endy": -50.0, 
      "endx": -1090.0, 
      "layer": "25", 
      "shape": "segment"
    }, 
    {
      "line_width": 320.0, 
      "startx": 0.0, 
      "starty": -450.0, 
      "endy": -50.0, 
      "endx": 0.0, 
      "layer": "25", 
      "shape": "segment"
    }, 
    {
      "line_width": 320.0, 
      "startx": 1090.0, 
      "starty": -450.0, 
      "endy": -50.0, 
      "endx": 1090.0, 
      "layer": "25", 
      "shape": "segment"
    }, 
    {
      "line_width": 320.0, 
      "startx": 540.0, 
      "starty": 550.0, 
      "endy": 950.0, 
      "endx": 540.0, 
      "layer": "25", 
      "shape": "segment"
    }, 
    {
      "line_width": 320.0, 
      "startx": -540.0, 
      "starty": 550.0, 
      "endy": 950.0, 
      "endx": -540.0, 
      "layer": "25", 
      "shape": "segment"
    }, 
    {
      "line_width": 320.0, 
      "startx": -1630.0, 
      "starty": 550.0, 
      "endy": 950.0, 
      "endx": -1630.0, 
      "layer": "25", 
      "shape": "segment"
    }, 
    {
      "line_width": 320.0, 
      "startx": -2170.0, 
      "starty": -450.0, 
      "endy": -50.0, 
      "endx": -2170.0, 
      "layer": "25", 
      "shape": "segment"
    }, 
    {
      "line_width": 320.0, 
      "startx": -2720.0, 
      "starty": 550.0, 
      "endy": 950.0, 
      "endx": -2720.0, 
      "layer": "25", 
      "shape": "segment"
    }, 
    {
      "line_width": 320.0, 
      "startx": -3260.0, 
      "starty": -450.0, 
      "endy": -50.0, 
      "endx": -3260.0, 
      "layer": "25", 
      "shape": "segment"
    }, 
    {
      "line_width": 60.0, 
      "startx": -8450.0, 
      "starty": 3000.0, 
      "endy": 3000.0, 
      "endx": -10450.0, 
      "layer": "21", 
      "shape": "segment"
    }, 
    {
      "line_width": 60.0, 
      "startx": -7650.0, 
      "starty": 4600.0, 
      "endy": 4600.0, 
      "endx": -10450.0, 
      "layer": "21", 
      "shape": "segment"
    }, 
    {
      "line_width": 60.0, 
      "startx": -7800.0, 
      "starty": 4850.0, 
      "endy": 6700.0, 
      "endx": -7800.0, 
      "layer": "21", 
      "shape": "segment"
    }, 
    {
      "line_width": 60.0, 
      "layer": "21", 
      "angle": 1.5707963267948966, 
      "start_angle": -1.5707963267948966, 
      "shape": "arc", 
      "r": 250.0, 
      "start_x": "-8050", 
      "start_y": "4600", 
      "y": "4850", 
      "x": "-8050"
    }, 
    {
      "line_width": 60.0, 
      "startx": 10450.0, 
      "starty": 4600.0, 
      "endy": 4600.0, 
      "endx": 7650.0, 
      "layer": "21", 
      "shape": "segment"
    }, 
    {
      "line_width": 60.0, 
      "startx": 7800.0, 
      "starty": 4850.0, 
      "endy": 6700.0, 
      "endx": 7800.0, 
      "layer": "21", 
      "shape": "segment"
    }, 
    {
      "line_width": 60.0, 
      "layer": "21", 
      "angle": 1.5707963267948966, 
      "start_angle": 3.141592653589793, 
      "shape": "arc", 
      "r": 250.0, 
      "start_x": "7800", 
      "start_y": "4850", 
      "y": "4850", 
      "x": "8050"
    }, 
    {
      "line_width": 320.0, 
      "startx": -3800.0, 
      "starty": 540.0, 
      "endy": 940.0, 
      "endx": -3800.0, 
      "layer": "25", 
      "shape": "segment"
    }, 
    {
      "line_width": 320.0, 
      "startx": -4350.0, 
      "starty": -450.0, 
      "endy": -50.0, 
      "endx": -4350.0, 
      "layer": "25", 
      "shape": "segment"
    }, 
    {
      "line_width": 320.0, 
      "startx": 1630.0, 
      "starty": 550.0, 
      "endy": 950.0, 
      "endx": 1630.0, 
      "layer": "25", 
      "shape": "segment"
    }, 
    {
      "line_width": 320.0, 
      "startx": 2170.0, 
      "starty": -450.0, 
      "endy": -50.0, 
      "endx": 2170.0, 
      "layer": "25", 
      "shape": "segment"
    }, 
    {
      "line_width": 320.0, 
      "startx": 2720.0, 
      "starty": 550.0, 
      "endy": 950.0, 
      "endx": 2720.0, 
      "layer": "25", 
      "shape": "segment"
    }, 
    {
      "line_width": 320.0, 
      "startx": 3260.0, 
      "starty": -450.0, 
      "endy": -50.0, 
      "endx": 3260.0, 
      "layer": "25", 
      "shape": "segment"
    }, 
    {
      "line_width": 320.0, 
      "startx": 3800.0, 
      "starty": 550.0, 
      "endy": 950.0, 
      "endx": 3800.0, 
      "layer": "25", 
      "shape": "segment"
    }, 
    {
      "line_width": 320.0, 
      "startx": 4350.0, 
      "starty": -450.0, 
      "endy": -50.0, 
      "endx": 4350.0, 
      "layer": "25", 
      "shape": "segment"
    }, 
    {
      "line_width": 320.0, 
      "startx": 5430.0, 
      "starty": -450.0, 
      "endy": -50.0, 
      "endx": 5430.0, 
      "layer": "25", 
      "shape": "segment"
    }, 
    {
      "line_width": 320.0, 
      "startx": 4890.0, 
      "starty": 550.0, 
      "endy": 950.0, 
      "endx": 4890.0, 
      "layer": "25", 
      "shape": "segment"
    }, 
    {
      "line_width": 60.0, 
      "startx": 6520.0, 
      "starty": -450.0, 
      "endy": -50.0, 
      "endx": 6520.0, 
      "layer": "25", 
      "shape": "segment"
    }, 
    {
      "line_width": 320.0, 
      "startx": 5980.0, 
      "starty": 550.0, 
      "endy": 950.0, 
      "endx": 5980.0, 
      "layer": "25", 
      "shape": "segment"
    }, 
    {
      "line_width": 320.0, 
      "startx": -5430.0, 
      "starty": -450.0, 
      "endy": -50.0, 
      "endx": -5430.0, 
      "layer": "25", 
      "shape": "segment"
    }, 
    {
      "line_width": 320.0, 
      "startx": -4890.0, 
      "starty": 540.0, 
      "endy": 940.0, 
      "endx": -4890.0, 
      "layer": "25", 
      "shape": "segment"
    }, 
    {
      "line_width": 320.0, 
      "startx": -5980.0, 
      "starty": 540.0, 
      "endy": 940.0, 
      "endx": -5980.0, 
      "layer": "25", 
      "shape": "segment"
    }, 
    {
      "line_width": 320.0, 
      "startx": -6520.0, 
      "starty": -450.0, 
      "endy": -50.0, 
      "endx": -6520.0, 
      "layer": "25", 
      "shape": "segment"
    }, 
    {
      "line_width": 60.0, 
      "startx": -7500.0, 
      "starty": 6900.0, 
      "endy": 6900.0, 
      "endx": -7600.0, 
      "layer": "21", 
      "shape": "segment"
    }, 
    {
      "line_width": 60.0, 
      "startx": 7500.0, 
      "starty": 6900.0, 
      "endy": 6900.0, 
      "endx": -7500.0, 
      "layer": "21", 
      "shape": "segment"
    }, 
    {
      "line_width": 60.0, 
      "layer": "21", 
      "shape": "circle", 
      "r": 650.0, 
      "y": 0.0, 
      "x": 9260.0
    }, 
    {
      "line_width": 0.0, 
      "layer": "24", 
      "shape": "circle", 
      "r": 1050.0, 
      "y": 0.0, 
      "x": 9260.0
    }, 
    {
      "line_width": 0.0, 
      "layer": "24", 
      "shape": "circle", 
      "r": 1050.0, 
      "y": 0.0, 
      "x": 9260.0
    }, 
    {
      "line_width": 0.0, 
      "layer": "24", 
      "shape": "circle", 
      "r": 1050.0, 
      "y": 0.0, 
      "x": -9260.0
    }, 
    {
      "line_width": 0.0, 
      "layer": "24", 
      "shape": "circle", 
      "r": 1050.0, 
      "y": 0.0, 
      "x": -9260.0
    }, 
    {
      "line_width": 60.0, 
      "layer": "21", 
      "shape": "circle", 
      "r": 650.0, 
      "y": 0.0, 
      "x": -9260.0
    }, 
    {
      "line_width": 50.0, 
      "startx": -10450.0, 
      "starty": 4600.0, 
      "endy": 4600.0, 
      "endx": 10450.0, 
      "layer": "21", 
      "shape": "segment"
    }, 
    {
      "line_width": 50.0, 
      "startx": 10450.0, 
      "starty": 4600.0, 
      "endy": 4400.0, 
      "endx": 10450.0, 
      "layer": "21", 
      "shape": "segment"
    }, 
    {
      "line_width": 50.0, 
      "startx": 10450.0, 
      "starty": 4400.0, 
      "endy": 4400.0, 
      "endx": -10450.0, 
      "layer": "21", 
      "shape": "segment"
    }, 
    {
      "line_width": 50.0, 
      "startx": -10450.0, 
      "starty": 4400.0, 
      "endy": 4600.0, 
      "endx": -10450.0, 
      "layer": "21", 
      "shape": "segment"
    }, 
    {
      "line_width": 50.0, 
      "startx": -8000.0, 
      "starty": 3000.0, 
      "endy": 3000.0, 
      "endx": 8000.0, 
      "layer": "21", 
      "shape": "segment"
    }, 
    {
      "line_width": 50.0, 
      "startx": 8000.0, 
      "starty": 3000.0, 
      "endy": 2700.0, 
      "endx": 8000.0, 
      "layer": "21", 
      "shape": "segment"
    }, 
    {
      "line_width": 50.0, 
      "startx": 8000.0, 
      "starty": 2700.0, 
      "endy": 2700.0, 
      "endx": -8000.0, 
      "layer": "21", 
      "shape": "segment"
    }, 
    {
      "line_width": 50.0, 
      "startx": -8000.0, 
      "starty": 2700.0, 
      "endy": 3000.0, 
      "endx": -8000.0, 
      "layer": "21", 
      "shape": "segment"
    }, 
    {
      "line_width": 50.0, 
      "startx": -6679.0, 
      "starty": 2700.0, 
      "endy": 2700.0, 
      "endx": -6360.0, 
      "layer": "21", 
      "shape": "segment"
    }, 
    {
      "line_width": 50.0, 
      "startx": -6360.0, 
      "starty": 2700.0, 
      "endy": -150.0, 
      "endx": -6360.0, 
      "layer": "21", 
      "shape": "segment"
    }, 
    {
      "line_width": 50.0, 
      "startx": -6360.0, 
      "starty": -150.0, 
      "endy": -150.0, 
      "endx": -6679.0, 
      "layer": "21", 
      "shape": "segment"
    }, 
    {
      "line_width": 50.0, 
      "startx": -6679.0, 
      "starty": -150.0, 
      "endy": 2700.0, 
      "endx": -6679.0, 
      "layer": "21", 
      "shape": "segment"
    }, 
    {
      "line_width": 50.0, 
      "startx": -6140.0, 
      "starty": 2700.0, 
      "endy": 2700.0, 
      "endx": -5820.0, 
      "layer": "21", 
      "shape": "segment"
    }, 
    {
      "line_width": 50.0, 
      "startx": -5820.0, 
      "starty": 2700.0, 
      "endy": 850.0, 
      "endx": -5820.0, 
      "layer": "21", 
      "shape": "segment"
    }, 
    {
      "line_width": 50.0, 
      "startx": -5820.0, 
      "starty": 850.0, 
      "endy": 850.0, 
      "endx": -6140.0, 
      "layer": "21", 
      "shape": "segment"
    }, 
    {
      "line_width": 50.0, 
      "startx": -6140.0, 
      "starty": 850.0, 
      "endy": 2700.0, 
      "endx": -6140.0, 
      "layer": "21", 
      "shape": "segment"
    }, 
    {
      "line_width": 50.0, 
      "startx": -5590.0, 
      "starty": 2700.0, 
      "endy": 2700.0, 
      "endx": -5270.0, 
      "layer": "21", 
      "shape": "segment"
    }, 
    {
      "line_width": 50.0, 
      "startx": -5270.0, 
      "starty": 2700.0, 
      "endy": -150.0, 
      "endx": -5270.0, 
      "layer": "21", 
      "shape": "segment"
    }, 
    {
      "line_width": 50.0, 
      "startx": -5270.0, 
      "starty": -150.0, 
      "endy": -150.0, 
      "endx": -5590.0, 
      "layer": "21", 
      "shape": "segment"
    }, 
    {
      "line_width": 50.0, 
      "startx": -5590.0, 
      "starty": -150.0, 
      "endy": 2700.0, 
      "endx": -5590.0, 
      "layer": "21", 
      "shape": "segment"
    }, 
    {
      "line_width": 50.0, 
      "startx": -5050.0, 
      "starty": 2700.0, 
      "endy": 2700.0, 
      "endx": -4730.0, 
      "layer": "21", 
      "shape": "segment"
    }, 
    {
      "line_width": 50.0, 
      "startx": -4730.0, 
      "starty": 2700.0, 
      "endy": 850.0, 
      "endx": -4730.0, 
      "layer": "21", 
      "shape": "segment"
    }, 
    {
      "line_width": 50.0, 
      "startx": -4730.0, 
      "starty": 850.0, 
      "endy": 850.0, 
      "endx": -5050.0, 
      "layer": "21", 
      "shape": "segment"
    }, 
    {
      "line_width": 50.0, 
      "startx": -5050.0, 
      "starty": 850.0, 
      "endy": 2700.0, 
      "endx": -5050.0, 
      "layer": "21", 
      "shape": "segment"
    }, 
    {
      "line_width": 50.0, 
      "startx": -4510.0, 
      "starty": 2700.0, 
      "endy": 2700.0, 
      "endx": -4190.0, 
      "layer": "21", 
      "shape": "segment"
    }, 
    {
      "line_width": 50.0, 
      "startx": -4190.0, 
      "starty": 2700.0, 
      "endy": -150.0, 
      "endx": -4190.0, 
      "layer": "21", 
      "shape": "segment"
    }, 
    {
      "line_width": 50.0, 
      "startx": -4190.0, 
      "starty": -150.0, 
      "endy": -150.0, 
      "endx": -4510.0, 
      "layer": "21", 
      "shape": "segment"
    }, 
    {
      "line_width": 50.0, 
      "startx": -4510.0, 
      "starty": -150.0, 
      "endy": 2700.0, 
      "endx": -4510.0, 
      "layer": "21", 
      "shape": "segment"
    }, 
    {
      "line_width": 50.0, 
      "startx": -3960.0, 
      "starty": 2700.0, 
      "endy": 2700.0, 
      "endx": -3640.0, 
      "layer": "21", 
      "shape": "segment"
    }, 
    {
      "line_width": 50.0, 
      "startx": -3640.0, 
      "starty": 2700.0, 
      "endy": 850.0, 
      "endx": -3640.0, 
      "layer": "21", 
      "shape": "segment"
    }, 
    {
      "line_width": 50.0, 
      "startx": -3640.0, 
      "starty": 850.0, 
      "endy": 850.0, 
      "endx": -3960.0, 
      "layer": "21", 
      "shape": "segment"
    }, 
    {
      "line_width": 50.0, 
      "startx": -3960.0, 
      "starty": 850.0, 
      "endy": 2700.0, 
      "endx": -3960.0, 
      "layer": "21", 
      "shape": "segment"
    }, 
    {
      "line_width": 50.0, 
      "startx": -3420.0, 
      "starty": 2700.0, 
      "endy": 2700.0, 
      "endx": -3100.0, 
      "layer": "21", 
      "shape": "segment"
    }, 
    {
      "line_width": 50.0, 
      "startx": -3100.0, 
      "starty": 2700.0, 
      "endy": -150.0, 
      "endx": -3100.0, 
      "layer": "21", 
      "shape": "segment"
    }, 
    {
      "line_width": 50.0, 
      "startx": -3100.0, 
      "starty": -150.0, 
      "endy": -150.0, 
      "endx": -3420.0, 
      "layer": "21", 
      "shape": "segment"
    }, 
    {
      "line_width": 50.0, 
      "startx": -3420.0, 
      "starty": -150.0, 
      "endy": 2700.0, 
      "endx": -3420.0, 
      "layer": "21", 
      "shape": "segment"
    }, 
    {
      "line_width": 50.0, 
      "startx": -2880.0, 
      "starty": 2700.0, 
      "endy": 2700.0, 
      "endx": -2560.0, 
      "layer": "21", 
      "shape": "segment"
    }, 
    {
      "line_width": 50.0, 
      "startx": -2560.0, 
      "starty": 2700.0, 
      "endy": 850.0, 
      "endx": -2560.0, 
      "layer": "21", 
      "shape": "segment"
    }, 
    {
      "line_width": 50.0, 
      "startx": -2560.0, 
      "starty": 850.0, 
      "endy": 850.0, 
      "endx": -2880.0, 
      "layer": "21", 
      "shape": "segment"
    }, 
    {
      "line_width": 50.0, 
      "startx": -2880.0, 
      "starty": 850.0, 
      "endy": 2700.0, 
      "endx": -2880.0, 
      "layer": "21", 
      "shape": "segment"
    }, 
    {
      "line_width": 50.0, 
      "startx": -2330.0, 
      "starty": 2700.0, 
      "endy": 2700.0, 
      "endx": -2010.0, 
      "layer": "21", 
      "shape": "segment"
    }, 
    {
      "line_width": 50.0, 
      "startx": -2010.0, 
      "starty": 2700.0, 
      "endy": -150.0, 
      "endx": -2010.0, 
      "layer": "21", 
      "shape": "segment"
    }, 
    {
      "line_width": 50.0, 
      "startx": -2010.0, 
      "starty": -150.0, 
      "endy": -150.0, 
      "endx": -2330.0, 
      "layer": "21", 
      "shape": "segment"
    }, 
    {
      "line_width": 50.0, 
      "startx": -2330.0, 
      "starty": -150.0, 
      "endy": 2700.0, 
      "endx": -2330.0, 
      "layer": "21", 
      "shape": "segment"
    }, 
    {
      "line_width": 50.0, 
      "startx": -1790.0, 
      "starty": 2700.0, 
      "endy": 2700.0, 
      "endx": -1470.0, 
      "layer": "21", 
      "shape": "segment"
    }, 
    {
      "line_width": 50.0, 
      "startx": -1470.0, 
      "starty": 2700.0, 
      "endy": 850.0, 
      "endx": -1470.0, 
      "layer": "21", 
      "shape": "segment"
    }, 
    {
      "line_width": 50.0, 
      "startx": -1470.0, 
      "starty": 850.0, 
      "endy": 850.0, 
      "endx": -1790.0, 
      "layer": "21", 
      "shape": "segment"
    }, 
    {
      "line_width": 50.0, 
      "startx": -1790.0, 
      "starty": 850.0, 
      "endy": 2700.0, 
      "endx": -1790.0, 
      "layer": "21", 
      "shape": "segment"
    }, 
    {
      "line_width": 50.0, 
      "startx": -1250.0, 
      "starty": 2700.0, 
      "endy": 2700.0, 
      "endx": -930.0, 
      "layer": "21", 
      "shape": "segment"
    }, 
    {
      "line_width": 50.0, 
      "startx": -930.0, 
      "starty": 2700.0, 
      "endy": -150.0, 
      "endx": -930.0, 
      "layer": "21", 
      "shape": "segment"
    }, 
    {
      "line_width": 50.0, 
      "startx": -930.0, 
      "starty": -150.0, 
      "endy": -150.0, 
      "endx": -1250.0, 
      "layer": "21", 
      "shape": "segment"
    }, 
    {
      "line_width": 50.0, 
      "startx": -1250.0, 
      "starty": -150.0, 
      "endy": 2700.0, 
      "endx": -1250.0, 
      "layer": "21", 
      "shape": "segment"
    }, 
    {
      "line_width": 50.0, 
      "startx": -700.0, 
      "starty": 2700.0, 
      "endy": 2700.0, 
      "endx": -380.0, 
      "layer": "21", 
      "shape": "segment"
    }, 
    {
      "line_width": 50.0, 
      "startx": -380.0, 
      "starty": 2700.0, 
      "endy": 850.0, 
      "endx": -380.0, 
      "layer": "21", 
      "shape": "segment"
    }, 
    {
      "line_width": 50.0, 
      "startx": -380.0, 
      "starty": 850.0, 
      "endy": 850.0, 
      "endx": -700.0, 
      "layer": "21", 
      "shape": "segment"
    }, 
    {
      "line_width": 50.0, 
      "startx": -700.0, 
      "starty": 850.0, 
      "endy": 2700.0, 
      "endx": -700.0, 
      "layer": "21", 
      "shape": "segment"
    }, 
    {
      "line_width": 50.0, 
      "startx": -160.0, 
      "starty": 2700.0, 
      "endy": 2700.0, 
      "endx": 160.0, 
      "layer": "21", 
      "shape": "segment"
    }, 
    {
      "line_width": 50.0, 
      "startx": 160.0, 
      "starty": 2700.0, 
      "endy": -150.0, 
      "endx": 160.0, 
      "layer": "21", 
      "shape": "segment"
    }, 
    {
      "line_width": 50.0, 
      "startx": 160.0, 
      "starty": -150.0, 
      "endy": -150.0, 
      "endx": -160.0, 
      "layer": "21", 
      "shape": "segment"
    }, 
    {
      "line_width": 50.0, 
      "startx": -160.0, 
      "starty": -150.0, 
      "endy": 2700.0, 
      "endx": -160.0, 
      "layer": "21", 
      "shape": "segment"
    }, 
    {
      "line_width": 50.0, 
      "startx": 380.0, 
      "starty": 2700.0, 
      "endy": 2700.0, 
      "endx": 700.0, 
      "layer": "21", 
      "shape": "segment"
    }, 
    {
      "line_width": 50.0, 
      "startx": 700.0, 
      "starty": 2700.0, 
      "endy": 850.0, 
      "endx": 700.0, 
      "layer": "21", 
      "shape": "segment"
    }, 
    {
      "line_width": 50.0, 
      "startx": 700.0, 
      "starty": 850.0, 
      "endy": 850.0, 
      "endx": 380.0, 
      "layer": "21", 
      "shape": "segment"
    }, 
    {
      "line_width": 50.0, 
      "startx": 380.0, 
      "starty": 850.0, 
      "endy": 2700.0, 
      "endx": 380.0, 
      "layer": "21", 
      "shape": "segment"
    }, 
    {
      "line_width": 50.0, 
      "startx": 930.0, 
      "starty": 2700.0, 
      "endy": 2700.0, 
      "endx": 1250.0, 
      "layer": "21", 
      "shape": "segment"
    }, 
    {
      "line_width": 50.0, 
      "startx": 1250.0, 
      "starty": 2700.0, 
      "endy": -150.0, 
      "endx": 1250.0, 
      "layer": "21", 
      "shape": "segment"
    }, 
    {
      "line_width": 50.0, 
      "startx": 1250.0, 
      "starty": -150.0, 
      "endy": -150.0, 
      "endx": 930.0, 
      "layer": "21", 
      "shape": "segment"
    }, 
    {
      "line_width": 50.0, 
      "startx": 930.0, 
      "starty": -150.0, 
      "endy": 2700.0, 
      "endx": 930.0, 
      "layer": "21", 
      "shape": "segment"
    }, 
    {
      "line_width": 50.0, 
      "startx": 1470.0, 
      "starty": 2700.0, 
      "endy": 2700.0, 
      "endx": 1790.0, 
      "layer": "21", 
      "shape": "segment"
    }, 
    {
      "line_width": 50.0, 
      "startx": 1790.0, 
      "starty": 2700.0, 
      "endy": 850.0, 
      "endx": 1790.0, 
      "layer": "21", 
      "shape": "segment"
    }, 
    {
      "line_width": 50.0, 
      "startx": 1790.0, 
      "starty": 850.0, 
      "endy": 850.0, 
      "endx": 1470.0, 
      "layer": "21", 
      "shape": "segment"
    }, 
    {
      "line_width": 50.0, 
      "startx": 1470.0, 
      "starty": 850.0, 
      "endy": 2700.0, 
      "endx": 1470.0, 
      "layer": "21", 
      "shape": "segment"
    }, 
    {
      "line_width": 50.0, 
      "startx": 2010.0, 
      "starty": 2700.0, 
      "endy": 2700.0, 
      "endx": 2330.0, 
      "layer": "21", 
      "shape": "segment"
    }, 
    {
      "line_width": 50.0, 
      "startx": 2330.0, 
      "starty": 2700.0, 
      "endy": -150.0, 
      "endx": 2330.0, 
      "layer": "21", 
      "shape": "segment"
    }, 
    {
      "line_width": 50.0, 
      "startx": 2330.0, 
      "starty": -150.0, 
      "endy": -150.0, 
      "endx": 2010.0, 
      "layer": "21", 
      "shape": "segment"
    }, 
    {
      "line_width": 50.0, 
      "startx": 2010.0, 
      "starty": -150.0, 
      "endy": 2700.0, 
      "endx": 2010.0, 
      "layer": "21", 
      "shape": "segment"
    }, 
    {
      "line_width": 50.0, 
      "startx": 2560.0, 
      "starty": 2700.0, 
      "endy": 2700.0, 
      "endx": 2880.0, 
      "layer": "21", 
      "shape": "segment"
    }, 
    {
      "line_width": 50.0, 
      "startx": 2880.0, 
      "starty": 2700.0, 
      "endy": 850.0, 
      "endx": 2880.0, 
      "layer": "21", 
      "shape": "segment"
    }, 
    {
      "line_width": 50.0, 
      "startx": 2880.0, 
      "starty": 850.0, 
      "endy": 850.0, 
      "endx": 2560.0, 
      "layer": "21", 
      "shape": "segment"
    }, 
    {
      "line_width": 50.0, 
      "startx": 2560.0, 
      "starty": 850.0, 
      "endy": 2700.0, 
      "endx": 2560.0, 
      "layer": "21", 
      "shape": "segment"
    }, 
    {
      "line_width": 50.0, 
      "startx": 3100.0, 
      "starty": 2700.0, 
      "endy": 2700.0, 
      "endx": 3420.0, 
      "layer": "21", 
      "shape": "segment"
    }, 
    {
      "line_width": 50.0, 
      "startx": 3420.0, 
      "starty": 2700.0, 
      "endy": -150.0, 
      "endx": 3420.0, 
      "layer": "21", 
      "shape": "segment"
    }, 
    {
      "line_width": 50.0, 
      "startx": 3420.0, 
      "starty": -150.0, 
      "endy": -150.0, 
      "endx": 3100.0, 
      "layer": "21", 
      "shape": "segment"
    }, 
    {
      "line_width": 50.0, 
      "startx": 3100.0, 
      "starty": -150.0, 
      "endy": 2700.0, 
      "endx": 3100.0, 
      "layer": "21", 
      "shape": "segment"
    }, 
    {
      "line_width": 50.0, 
      "startx": 3640.0, 
      "starty": 2700.0, 
      "endy": 2700.0, 
      "endx": 3960.0, 
      "layer": "21", 
      "shape": "segment"
    }, 
    {
      "line_width": 50.0, 
      "startx": 3960.0, 
      "starty": 2700.0, 
      "endy": 850.0, 
      "endx": 3960.0, 
      "layer": "21", 
      "shape": "segment"
    }, 
    {
      "line_width": 50.0, 
      "startx": 3960.0, 
      "starty": 850.0, 
      "endy": 850.0, 
      "endx": 3640.0, 
      "layer": "21", 
      "shape": "segment"
    }, 
    {
      "line_width": 50.0, 
      "startx": 3640.0, 
      "starty": 850.0, 
      "endy": 2700.0, 
      "endx": 3640.0, 
      "layer": "21", 
      "shape": "segment"
    }, 
    {
      "line_width": 50.0, 
      "startx": 4190.0, 
      "starty": 2700.0, 
      "endy": 2700.0, 
      "endx": 4510.0, 
      "layer": "21", 
      "shape": "segment"
    }, 
    {
      "line_width": 50.0, 
      "startx": 4510.0, 
      "starty": 2700.0, 
      "endy": -150.0, 
      "endx": 4510.0, 
      "layer": "21", 
      "shape": "segment"
    }, 
    {
      "line_width": 50.0, 
      "startx": 4510.0, 
      "starty": -150.0, 
      "endy": -150.0, 
      "endx": 4190.0, 
      "layer": "21", 
      "shape": "segment"
    }, 
    {
      "line_width": 50.0, 
      "startx": 4190.0, 
      "starty": -150.0, 
      "endy": 2700.0, 
      "endx": 4190.0, 
      "layer": "21", 
      "shape": "segment"
    }, 
    {
      "line_width": 50.0, 
      "startx": 4730.0, 
      "starty": 2700.0, 
      "endy": 2700.0, 
      "endx": 5050.0, 
      "layer": "21", 
      "shape": "segment"
    }, 
    {
      "line_width": 50.0, 
      "startx": 5050.0, 
      "starty": 2700.0, 
      "endy": 850.0, 
      "endx": 5050.0, 
      "layer": "21", 
      "shape": "segment"
    }, 
    {
      "line_width": 50.0, 
      "startx": 5050.0, 
      "starty": 850.0, 
      "endy": 850.0, 
      "endx": 4730.0, 
      "layer": "21", 
      "shape": "segment"
    }, 
    {
      "line_width": 50.0, 
      "startx": 4730.0, 
      "starty": 850.0, 
      "endy": 2700.0, 
      "endx": 4730.0, 
      "layer": "21", 
      "shape": "segment"
    }, 
    {
      "line_width": 50.0, 
      "startx": 5270.0, 
      "starty": 2700.0, 
      "endy": 2700.0, 
      "endx": 5590.0, 
      "layer": "21", 
      "shape": "segment"
    }, 
    {
      "line_width": 50.0, 
      "startx": 5590.0, 
      "starty": 2700.0, 
      "endy": -150.0, 
      "endx": 5590.0, 
      "layer": "21", 
      "shape": "segment"
    }, 
    {
      "line_width": 50.0, 
      "startx": 5590.0, 
      "starty": -150.0, 
      "endy": -150.0, 
      "endx": 5270.0, 
      "layer": "21", 
      "shape": "segment"
    }, 
    {
      "line_width": 50.0, 
      "startx": 5270.0, 
      "starty": -150.0, 
      "endy": 2700.0, 
      "endx": 5270.0, 
      "layer": "21", 
      "shape": "segment"
    }, 
    {
      "line_width": 50.0, 
      "startx": 5820.0, 
      "starty": 2700.0, 
      "endy": 2700.0, 
      "endx": 6140.0, 
      "layer": "21", 
      "shape": "segment"
    }, 
    {
      "line_width": 50.0, 
      "startx": 6140.0, 
      "starty": 2700.0, 
      "endy": 850.0, 
      "endx": 6140.0, 
      "layer": "21", 
      "shape": "segment"
    }, 
    {
      "line_width": 50.0, 
      "startx": 6140.0, 
      "starty": 850.0, 
      "endy": 850.0, 
      "endx": 5820.0, 
      "layer": "21", 
      "shape": "segment"
    }, 
    {
      "line_width": 50.0, 
      "startx": 5820.0, 
      "starty": 850.0, 
      "endy": 2700.0, 
      "endx": 5820.0, 
      "layer": "21", 
      "shape": "segment"
    }, 
    {
      "line_width": 50.0, 
      "startx": 6360.0, 
      "starty": 2700.0, 
      "endy": 2700.0, 
      "endx": 6679.0, 
      "layer": "21", 
      "shape": "segment"
    }, 
    {
      "line_width": 50.0, 
      "startx": 6679.0, 
      "starty": 2700.0, 
      "endy": -150.0, 
      "endx": 6679.0, 
      "layer": "21", 
      "shape": "segment"
    }, 
    {
      "line_width": 50.0, 
      "startx": 6679.0, 
      "starty": -150.0, 
      "endy": -150.0, 
      "endx": 6360.0, 
      "layer": "21", 
      "shape": "segment"
    }, 
    {
      "line_width": 50.0, 
      "startx": 6360.0, 
      "starty": -150.0, 
      "endy": 2700.0, 
      "endx": 6360.0, 
      "layer": "21", 
      "shape": "segment"
    }
  ], 
  "name": "M25H", 
  "keyword": [
    " <b>SUB-D</b>"
  ], 
  "text": [
    {
      "layer": "26", 
      "angle": 0.0, 
      "misc": " \">NAME\"", 
      "sizex": 700.0, 
      "number": "0", 
      "sizey": 700.0, 
      "visible": true, 
      "flag": "N", 
      "text": ">NAME", 
      "y": -1400.0, 
      "x": -9000.0, 
      "rotation": "0", 
      "penwidth": 70.0
    }, 
    {
      "layer": "26", 
      "angle": 0.0, 
      "misc": " \">VALUE\"", 
      "sizex": 700.0, 
      "number": "1", 
      "sizey": 700.0, 
      "visible": true, 
      "flag": "N", 
      "text": ">VALUE", 
      "y": 8400.0, 
      "x": -4900.0, 
      "rotation": "0", 
      "penwidth": 70.0
    }, 
    {
      "layer": "21", 
      "angle": 0.0, 
      "misc": " \"1\"", 
      "sizex": 500.0, 
      "number": "2", 
      "sizey": 500.0, 
      "visible": true, 
      "flag": "N", 
      "text": "1", 
      "y": 0.0, 
      "x": -7350.0, 
      "rotation": "0", 
      "penwidth": 50.0
    }, 
    {
      "layer": "21", 
      "angle": 0.0, 
      "misc": " \"13\"", 
      "sizex": 500.0, 
      "number": "3", 
      "sizey": 500.0, 
      "visible": true, 
      "flag": "N", 
      "text": "13", 
      "y": 0.0, 
      "x": 7550.0, 
      "rotation": "0", 
      "penwidth": 50.0
    }, 
    {
      "layer": "21", 
      "angle": 0.0, 
      "misc": " \"14\"", 
      "sizex": 500.0, 
      "number": "4", 
      "sizey": 500.0, 
      "visible": true, 
      "flag": "N", 
      "text": "14", 
      "y": 1050.0, 
      "x": -7300.0, 
      "rotation": "0", 
      "penwidth": 50.0
    }, 
    {
      "layer": "21", 
      "angle": 0.0, 
      "misc": " \"25\"", 
      "sizex": 500.0, 
      "number": "5", 
      "sizey": 500.0, 
      "visible": true, 
      "flag": "N", 
      "text": "25", 
      "y": 1000.0, 
      "x": 7450.0, 
      "rotation": "0", 
      "penwidth": 50.0
    }, 
    {
      "layer": "21", 
      "angle": 1.5707963267948966, 
      "misc": " \"2,54\"", 
      "sizex": 500.0, 
      "number": "6", 
      "sizey": 500.0, 
      "visible": true, 
      "flag": "N", 
      "text": "2,54", 
      "y": 1700.0, 
      "x": -9950.0, 
      "rotation": "900", 
      "penwidth": 50.0
    }, 
    {
      "layer": "21", 
      "angle": 0.0, 
      "misc": " \"M25\"", 
      "sizex": 500.0, 
      "number": "7", 
      "sizey": 500.0, 
      "visible": true, 
      "flag": "N", 
      "text": "M25", 
      "y": 4100.0, 
      "x": -6850.0, 
      "rotation": "0", 
      "penwidth": 50.0
    }
  ], 
  "timestamp_op": "00000000", 
  "rotation_cost_180": "0", 
  "attribute2": "~~", 
  "y": 0.0, 
  "rotation_cost_misc": "0", 
  "pad": [
    {
      "angle": 0.0, 
      "name": "Hole", 
      "drill_diam": 1300.0, 
      "deltax": 0.0, 
      "deltay": 0.0, 
      "sizex": 1300.0, 
      "sizey": 1300.0, 
      "drill_x": 0.0, 
      "layer_mask": "00E0FFFF", 
      "shape": "circle", 
      "drill_y": 0.0, 
      "posy": 0.0, 
      "posx": 9260.0, 
      "shape_code": "C", 
      "type": "HOLE", 
      "drill_shape": "circle", 
      "orientation": 0
    }, 
    {
      "angle": 0.0, 
      "name": "Hole", 
      "drill_diam": 1300.0, 
      "deltax": 0.0, 
      "deltay": 0.0, 
      "sizex": 1300.0, 
      "sizey": 1300.0, 
      "drill_x": 0.0, 
      "layer_mask": "00E0FFFF", 
      "shape": "circle", 
      "drill_y": 0.0, 
      "posy": 0.0, 
      "posx": -9260.0, 
      "shape_code": "C", 
      "type": "HOLE", 
      "drill_shape": "circle", 
      "orientation": 0
    }, 
    {
      "angle": 0.0, 
      "name": "13", 
      "drill_diam": 400.0, 
      "deltax": 0.0, 
      "deltay": 0.0, 
      "sizex": 600.0, 
      "sizey": 600.0, 
      "drill_x": 0.0, 
      "layer_mask": "00C0FFFF", 
      "shape": "oblong", 
      "drill_y": 0.0, 
      "posy": -500.0, 
      "posx": 6520.0, 
      "shape_code": "O", 
      "type": "STD", 
      "drill_shape": "circle", 
      "orientation": 0
    }, 
    {
      "angle": 0.0, 
      "name": "12", 
      "drill_diam": 400.0, 
      "deltax": 0.0, 
      "deltay": 0.0, 
      "sizex": 600.0, 
      "sizey": 600.0, 
      "drill_x": 0.0, 
      "layer_mask": "00C0FFFF", 
      "shape": "oblong", 
      "drill_y": 0.0, 
      "posy": -500.0, 
      "posx": 5430.0, 
      "shape_code": "O", 
      "type": "STD", 
      "drill_shape": "circle", 
      "orientation": 0
    }, 
    {
      "angle": 0.0, 
      "name": "11", 
      "drill_diam": 400.0, 
      "deltax": 0.0, 
      "deltay": 0.0, 
      "sizex": 600.0, 
      "sizey": 600.0, 
      "drill_x": 0.0, 
      "layer_mask": "00C0FFFF", 
      "shape": "oblong", 
      "drill_y": 0.0, 
      "posy": -500.0, 
      "posx": 4350.0, 
      "shape_code": "O", 
      "type": "STD", 
      "drill_shape": "circle", 
      "orientation": 0
    }, 
    {
      "angle": 0.0, 
      "name": "10", 
      "drill_diam": 400.0, 
      "deltax": 0.0, 
      "deltay": 0.0, 
      "sizex": 600.0, 
      "sizey": 600.0, 
      "drill_x": 0.0, 
      "layer_mask": "00C0FFFF", 
      "shape": "oblong", 
      "drill_y": 0.0, 
      "posy": -500.0, 
      "posx": 3260.0, 
      "shape_code": "O", 
      "type": "STD", 
      "drill_shape": "circle", 
      "orientation": 0
    }, 
    {
      "angle": 0.0, 
      "name": "9", 
      "drill_diam": 400.0, 
      "deltax": 0.0, 
      "deltay": 0.0, 
      "sizex": 600.0, 
      "sizey": 600.0, 
      "drill_x": 0.0, 
      "layer_mask": "00C0FFFF", 
      "shape": "oblong", 
      "drill_y": 0.0, 
      "posy": -500.0, 
      "posx": 2170.0, 
      "shape_code": "O", 
      "type": "STD", 
      "drill_shape": "circle", 
      "orientation": 0
    }, 
    {
      "angle": 0.0, 
      "name": "8", 
      "drill_diam": 400.0, 
      "deltax": 0.0, 
      "deltay": 0.0, 
      "sizex": 600.0, 
      "sizey": 600.0, 
      "drill_x": 0.0, 
      "layer_mask": "00C0FFFF", 
      "shape": "oblong", 
      "drill_y": 0.0, 
      "posy": -500.0, 
      "posx": 1090.0, 
      "shape_code": "O", 
      "type": "STD", 
      "drill_shape": "circle", 
      "orientation": 0
    }, 
    {
      "angle": 0.0, 
      "name": "7", 
      "drill_diam": 400.0, 
      "deltax": 0.0, 
      "deltay": 0.0, 
      "sizex": 600.0, 
      "sizey": 600.0, 
      "drill_x": 0.0, 
      "layer_mask": "00C0FFFF", 
      "shape": "oblong", 
      "drill_y": 0.0, 
      "posy": -500.0, 
      "posx": 0.0, 
      "shape_code": "O", 
      "type": "STD", 
      "drill_shape": "circle", 
      "orientation": 0
    }, 
    {
      "angle": 0.0, 
      "name": "6", 
      "drill_diam": 400.0, 
      "deltax": 0.0, 
      "deltay": 0.0, 
      "sizex": 600.0, 
      "sizey": 600.0, 
      "drill_x": 0.0, 
      "layer_mask": "00C0FFFF", 
      "shape": "oblong", 
      "drill_y": 0.0, 
      "posy": -500.0, 
      "posx": -1090.0, 
      "shape_code": "O", 
      "type": "STD", 
      "drill_shape": "circle", 
      "orientation": 0
    }, 
    {
      "angle": 0.0, 
      "name": "5", 
      "drill_diam": 400.0, 
      "deltax": 0.0, 
      "deltay": 0.0, 
      "sizex": 600.0, 
      "sizey": 600.0, 
      "drill_x": 0.0, 
      "layer_mask": "00C0FFFF", 
      "shape": "oblong", 
      "drill_y": 0.0, 
      "posy": -500.0, 
      "posx": -2170.0, 
      "shape_code": "O", 
      "type": "STD", 
      "drill_shape": "circle", 
      "orientation": 0
    }, 
    {
      "angle": 0.0, 
      "name": "4", 
      "drill_diam": 400.0, 
      "deltax": 0.0, 
      "deltay": 0.0, 
      "sizex": 600.0, 
      "sizey": 600.0, 
      "drill_x": 0.0, 
      "layer_mask": "00C0FFFF", 
      "shape": "oblong", 
      "drill_y": 0.0, 
      "posy": -500.0, 
      "posx": -3260.0, 
      "shape_code": "O", 
      "type": "STD", 
      "drill_shape": "circle", 
      "orientation": 0
    }, 
    {
      "angle": 0.0, 
      "name": "3", 
      "drill_diam": 400.0, 
      "deltax": 0.0, 
      "deltay": 0.0, 
      "sizex": 600.0, 
      "sizey": 600.0, 
      "drill_x": 0.0, 
      "layer_mask": "00C0FFFF", 
      "shape": "oblong", 
      "drill_y": 0.0, 
      "posy": -500.0, 
      "posx": -4350.0, 
      "shape_code": "O", 
      "type": "STD", 
      "drill_shape": "circle", 
      "orientation": 0
    }, 
    {
      "angle": 0.0, 
      "name": "2", 
      "drill_diam": 400.0, 
      "deltax": 0.0, 
      "deltay": 0.0, 
      "sizex": 600.0, 
      "sizey": 600.0, 
      "drill_x": 0.0, 
      "layer_mask": "00C0FFFF", 
      "shape": "oblong", 
      "drill_y": 0.0, 
      "posy": -500.0, 
      "posx": -5430.0, 
      "shape_code": "O", 
      "type": "STD", 
      "drill_shape": "circle", 
      "orientation": 0
    }, 
    {
      "angle": 0.0, 
      "name": "1", 
      "drill_diam": 400.0, 
      "deltax": 0.0, 
      "deltay": 0.0, 
      "sizex": 600.0, 
      "sizey": 600.0, 
      "drill_x": 0.0, 
      "layer_mask": "00C0FFFF", 
      "shape": "oblong", 
      "drill_y": 0.0, 
      "posy": -500.0, 
      "posx": -6520.0, 
      "shape_code": "O", 
      "type": "STD", 
      "drill_shape": "circle", 
      "orientation": 0
    }, 
    {
      "angle": 0.0, 
      "name": "25", 
      "drill_diam": 400.0, 
      "deltax": 0.0, 
      "deltay": 0.0, 
      "sizex": 600.0, 
      "sizey": 600.0, 
      "drill_x": 0.0, 
      "layer_mask": "00C0FFFF", 
      "shape": "oblong", 
      "drill_y": 0.0, 
      "posy": 500.0, 
      "posx": 5980.0, 
      "shape_code": "O", 
      "type": "STD", 
      "drill_shape": "circle", 
      "orientation": 0
    }, 
    {
      "angle": 0.0, 
      "name": "24", 
      "drill_diam": 400.0, 
      "deltax": 0.0, 
      "deltay": 0.0, 
      "sizex": 600.0, 
      "sizey": 600.0, 
      "drill_x": 0.0, 
      "layer_mask": "00C0FFFF", 
      "shape": "oblong", 
      "drill_y": 0.0, 
      "posy": 500.0, 
      "posx": 4890.0, 
      "shape_code": "O", 
      "type": "STD", 
      "drill_shape": "circle", 
      "orientation": 0
    }, 
    {
      "angle": 0.0, 
      "name": "23", 
      "drill_diam": 400.0, 
      "deltax": 0.0, 
      "deltay": 0.0, 
      "sizex": 600.0, 
      "sizey": 600.0, 
      "drill_x": 0.0, 
      "layer_mask": "00C0FFFF", 
      "shape": "oblong", 
      "drill_y": 0.0, 
      "posy": 500.0, 
      "posx": 3800.0, 
      "shape_code": "O", 
      "type": "STD", 
      "drill_shape": "circle", 
      "orientation": 0
    }, 
    {
      "angle": 0.0, 
      "name": "22", 
      "drill_diam": 400.0, 
      "deltax": 0.0, 
      "deltay": 0.0, 
      "sizex": 600.0, 
      "sizey": 600.0, 
      "drill_x": 0.0, 
      "layer_mask": "00C0FFFF", 
      "shape": "oblong", 
      "drill_y": 0.0, 
      "posy": 500.0, 
      "posx": 2720.0, 
      "shape_code": "O", 
      "type": "STD", 
      "drill_shape": "circle", 
      "orientation": 0
    }, 
    {
      "angle": 0.0, 
      "name": "21", 
      "drill_diam": 400.0, 
      "deltax": 0.0, 
      "deltay": 0.0, 
      "sizex": 600.0, 
      "sizey": 600.0, 
      "drill_x": 0.0, 
      "layer_mask": "00C0FFFF", 
      "shape": "oblong", 
      "drill_y": 0.0, 
      "posy": 500.0, 
      "posx": 1630.0, 
      "shape_code": "O", 
      "type": "STD", 
      "drill_shape": "circle", 
      "orientation": 0
    }, 
    {
      "angle": 0.0, 
      "name": "20", 
      "drill_diam": 400.0, 
      "deltax": 0.0, 
      "deltay": 0.0, 
      "sizex": 600.0, 
      "sizey": 600.0, 
      "drill_x": 0.0, 
      "layer_mask": "00C0FFFF", 
      "shape": "oblong", 
      "drill_y": 0.0, 
      "posy": 500.0, 
      "posx": 540.0, 
      "shape_code": "O", 
      "type": "STD", 
      "drill_shape": "circle", 
      "orientation": 0
    }, 
    {
      "angle": 0.0, 
      "name": "19", 
      "drill_diam": 400.0, 
      "deltax": 0.0, 
      "deltay": 0.0, 
      "sizex": 600.0, 
      "sizey": 600.0, 
      "drill_x": 0.0, 
      "layer_mask": "00C0FFFF", 
      "shape": "oblong", 
      "drill_y": 0.0, 
      "posy": 500.0, 
      "posx": -540.0, 
      "shape_code": "O", 
      "type": "STD", 
      "drill_shape": "circle", 
      "orientation": 0
    }, 
    {
      "angle": 0.0, 
      "name": "18", 
      "drill_diam": 400.0, 
      "deltax": 0.0, 
      "deltay": 0.0, 
      "sizex": 600.0, 
      "sizey": 600.0, 
      "drill_x": 0.0, 
      "layer_mask": "00C0FFFF", 
      "shape": "oblong", 
      "drill_y": 0.0, 
      "posy": 500.0, 
      "posx": -1630.0, 
      "shape_code": "O", 
      "type": "STD", 
      "drill_shape": "circle", 
      "orientation": 0
    }, 
    {
      "angle": 0.0, 
      "name": "17", 
      "drill_diam": 400.0, 
      "deltax": 0.0, 
      "deltay": 0.0, 
      "sizex": 600.0, 
      "sizey": 600.0, 
      "drill_x": 0.0, 
      "layer_mask": "00C0FFFF", 
      "shape": "oblong", 
      "drill_y": 0.0, 
      "posy": 500.0, 
      "posx": -2720.0, 
      "shape_code": "O", 
      "type": "STD", 
      "drill_shape": "circle", 
      "orientation": 0
    }, 
    {
      "angle": 0.0, 
      "name": "16", 
      "drill_diam": 400.0, 
      "deltax": 0.0, 
      "deltay": 0.0, 
      "sizex": 600.0, 
      "sizey": 600.0, 
      "drill_x": 0.0, 
      "layer_mask": "00C0FFFF", 
      "shape": "oblong", 
      "drill_y": 0.0, 
      "posy": 500.0, 
      "posx": -3800.0, 
      "shape_code": "O", 
      "type": "STD", 
      "drill_shape": "circle", 
      "orientation": 0
    }, 
    {
      "angle": 0.0, 
      "name": "15", 
      "drill_diam": 400.0, 
      "deltax": 0.0, 
      "deltay": 0.0, 
      "sizex": 600.0, 
      "sizey": 600.0, 
      "drill_x": 0.0, 
      "layer_mask": "00C0FFFF", 
      "shape": "oblong", 
      "drill_y": 0.0, 
      "posy": 500.0, 
      "posx": -4890.0, 
      "shape_code": "O", 
      "type": "STD", 
      "drill_shape": "circle", 
      "orientation": 0
    }, 
    {
      "angle": 0.0, 
      "name": "14", 
      "drill_diam": 400.0, 
      "deltax": 0.0, 
      "deltay": 0.0, 
      "sizex": 600.0, 
      "sizey": 600.0, 
      "drill_x": 0.0, 
      "layer_mask": "00C0FFFF", 
      "shape": "oblong", 
      "drill_y": 0.0, 
      "posy": 500.0, 
      "posx": -5980.0, 
      "shape_code": "O", 
      "type": "STD", 
      "drill_shape": "circle", 
      "orientation": 0
    }
  ], 
  "timestamp": "00000000", 
  "units": "deci-mils", 
  "x": 0.0, 
  "rotation_cost_90": "0", 
  "angle": 0.0, 
  "orientation": "0"
}